setup.py
Tools/__init__.py
moon_tools.egg-info/PKG-INFO
moon_tools.egg-info/SOURCES.txt
moon_tools.egg-info/dependency_links.txt
moon_tools.egg-info/top_level.txt