Metadata-Version: 1.0
Name: moon-tools
Version: 1.0.0
Summary: Moon's Dev tools
Home-page: https://github.com/moonChenHaohui/python_tools
Author: moon4Chen
Author-email: moon4chen@163.com
License: MIT Licence
Keywords: pip,moon-tools
Platform: any
